main.py
mseep_devto_agent-0.1.1.dist-info/METADATA
mseep_devto_agent-0.1.1.dist-info/WHEEL
mseep_devto_agent-0.1.1.dist-info/entry_points.txt
mseep_devto_agent-0.1.1.dist-info/top_level.txt
mseep_devto_agent-0.1.1.dist-info/RECORD
