Metadata-Version: 2.4
Name: mseep-devto-agent
Version: 0.1.1
Summary: Add your description here
Author-email: mseep <support@skydeck.ai>
Requires-Python: >=3.10
Requires-Dist: google-adk>=0.1.0
Requires-Dist: mcp[cli]>=1.9.1
Requires-Dist: requests>=2.32.3
Requires-Dist: termcolor>=3.1.0
